pyalioss_util/__init__.py
pyalioss_util/alioss_util.py
pyalioss_util-1.0.0.dist-info/LICENSE
pyalioss_util-1.0.0.dist-info/METADATA
pyalioss_util-1.0.0.dist-info/WHEEL
pyalioss_util-1.0.0.dist-info/top_level.txt
pyalioss_util-1.0.0.dist-info/zip-safe
pyalioss_util-1.0.0.dist-info/RECORD
