Metadata-Version: 2.1
Name: pyalioss_util
Version: 1.0.0
Summary: 阿里云oss助手
Home-page: https://github.com/buyfakett
Author: buyfakett
Author-email: buyfakett@vip.qq.com
License: MIT
Requires-Python: >=3.6
License-File: LICENSE
Requires-Dist: oss2
